intelliopsopenfgasdk_python/__init__.py
intelliopsopenfgasdk_python/http_client.py
intelliopsopenfgasdk_python/intelliops_openfga_sdk.py
intelliopsopenfgasdk_python/models.py
intelliopsopenfgasdk_python-0.2.9.dist-info/METADATA
intelliopsopenfgasdk_python-0.2.9.dist-info/WHEEL
intelliopsopenfgasdk_python-0.2.9.dist-info/RECORD
