Metadata-Version: 2.4
Name: intelliopsopenfgasdk-python
Version: 0.2.9
Summary: Add your description here
Author-email: buddhisenarathna <buddhi.senarathna@kodez.com.au>
Requires-Python: >=3.10
Requires-Dist: httpx==0.27.2
Requires-Dist: pydantic==2.10.6
